passbolt_client/__init__.py
passbolt_client/client.py
pybolt_client-1.0.3.dist-info/LICENSE
pybolt_client-1.0.3.dist-info/METADATA
pybolt_client-1.0.3.dist-info/WHEEL
pybolt_client-1.0.3.dist-info/top_level.txt
pybolt_client-1.0.3.dist-info/RECORD
