Metadata-Version: 2.1
Name: pybolt-client
Version: 1.0.3
Summary: "REST API Client for Passbolt servers."
License-File: LICENSE
Requires-Dist: requests (<3,>=2)
Requires-Dist: requests-gpgauthlib (==0.1.2)
Provides-Extra: test
Requires-Dist: black (==22.10.0) ; extra == 'test'
Requires-Dist: flake8-black (==0.3.5) ; extra == 'test'
Requires-Dist: flake8-builtins (==2.0.1) ; extra == 'test'
Requires-Dist: flake8-docstrings (==1.6.0) ; extra == 'test'
Requires-Dist: flake8-isort (==5.0.3) ; extra == 'test'
Requires-Dist: flake8-logging-format (==0.9.0) ; extra == 'test'
Requires-Dist: flake8-print (==5.0.0) ; extra == 'test'
Requires-Dist: flake8 (==4.0.1) ; extra == 'test'
Requires-Dist: isort (==5.10.1) ; extra == 'test'
Requires-Dist: pytest-flake8 (==1.1.1) ; extra == 'test'
Requires-Dist: pytest (==7.2.0) ; extra == 'test'
